LICENSE
README.md
pyproject.toml
setup.cfg
setup.py
geysermc/__init__.py
geysermc/py.typed
geysermc.egg-info/PKG-INFO
geysermc.egg-info/SOURCES.txt
geysermc.egg-info/dependency_links.txt
geysermc.egg-info/not-zip-safe
geysermc.egg-info/requires.txt
geysermc.egg-info/top_level.txt