Metadata-Version: 2.1
Name: geysermc
Version: 1.1.0
Summary: The unofficial Python wrapper for geysermc.org
Home-page: https://github.com/legopitstop/geysermc/
Author: Legopitstop
Author-email: contact@lpsmods.dev
License: MIT
Project-URL: Download, https://github.com/legopitstop/geysermc/releases
Project-URL: Documentation, https://docs.lpsmods.dev/geysermc
Project-URL: Source Code, https://github.com/legopitstop/geysermc
Keywords: Minecraft,GeyserMC
Classifier: Development Status :: 5 - Production/Stable
Classifier: Intended Audience :: Developers
Classifier: License :: OSI Approved :: MIT License
Classifier: Programming Language :: Python :: 3.12
Requires-Python: >=3.6
Provides-Extra: testing
License-File: LICENSE
